narsche/__init__.py
narsche-0.1.3.dist-info/licenses/LICENSE
tests/test_narsche.py
narsche-0.1.3.dist-info/METADATA
narsche-0.1.3.dist-info/WHEEL
narsche-0.1.3.dist-info/top_level.txt
narsche-0.1.3.dist-info/RECORD
