Metadata-Version: 2.4
Name: narsche
Version: 0.1.3
Summary: Computing schematicity of autobiographical narratives
Author-email: Isaac Kinley <isaac.kinley@gmail.com>
License-Expression: MIT
Requires-Python: >=3.9
License-File: LICENSE
Requires-Dist: networkx
Requires-Dist: spacy
Requires-Dist: wordfreq
Dynamic: license-file
